[
  { "id": 1, "name": "Norgu", "professionId": 5, "campaignId": 3, "unlock": "Nightfall — optional recruitment quest (Istan/mainland)" },
  { "id": 2, "name": "Goren", "professionId": 1, "campaignId": 3, "unlock": "Nightfall — optional recruitment quest (Kourna)" },
  { "id": 3, "name": "Tahlkora", "professionId": 3, "campaignId": 3, "unlock": "Nightfall — story, early Istan" },
  { "id": 4, "name": "Master of Whispers", "professionId": 4, "campaignId": 3, "unlock": "Nightfall — story branch in Kourna (mutually exclusive with Margrid until later)" },
  { "id": 5, "name": "Acolyte Jin", "professionId": 2, "campaignId": 3, "unlock": "Nightfall — story, Kourna" },
  { "id": 6, "name": "Koss", "professionId": 1, "campaignId": 3, "unlock": "Nightfall — story, early Istan" },
  { "id": 7, "name": "Dunkoro", "professionId": 3, "campaignId": 3, "unlock": "Nightfall — story, Istan" },
  { "id": 8, "name": "Acolyte Sousuke", "professionId": 6, "campaignId": 3, "unlock": "Nightfall — story, Kourna" },
  { "id": 9, "name": "Melonni", "professionId": 10, "campaignId": 3, "unlock": "Nightfall — story, early Istan" },
  { "id": 10, "name": "Zhed Shadowhoof", "professionId": 6, "campaignId": 3, "unlock": "Nightfall — story, Kourna" },
  { "id": 11, "name": "General Morgahn", "professionId": 9, "campaignId": 3, "unlock": "Nightfall — story, Vabbi" },
  { "id": 12, "name": "Margrid the Sly", "professionId": 2, "campaignId": 3, "unlock": "Nightfall — story branch in Kourna (mutually exclusive with Master of Whispers until later)" },
  { "id": 13, "name": "Zenmai", "professionId": 7, "campaignId": 2, "unlock": "Factions — quest in Kaineng Center (any campaign character)" },
  { "id": 14, "name": "Olias", "professionId": 4, "campaignId": 1, "unlock": "Prophecies-linked — quest from Lion's Arch area (any campaign character)" },
  { "id": 15, "name": "Razah", "professionId": 8, "campaignId": 3, "unlock": "Nightfall — post-story, Domain of Anguish quest chain" },
  { "id": 16, "name": "M.O.X.", "professionId": 10, "campaignId": 4, "unlock": "Free quest — requires Nightfall or Eye of the North" },
  { "id": 17, "name": "Keiran Thackeray", "professionId": 9, "campaignId": 4, "unlock": "Guild Wars Beyond — Hearts of the North epilogue" },
  { "id": 18, "name": "Jora", "professionId": 1, "campaignId": 4, "unlock": "Eye of the North — story, Norn questline" },
  { "id": 19, "name": "Pyre Fierceshot", "professionId": 2, "campaignId": 4, "unlock": "Eye of the North — story, Charr questline" },
  { "id": 20, "name": "Anton", "professionId": 7, "campaignId": 4, "unlock": "Eye of the North — Ebon Vanguard quest" },
  { "id": 21, "name": "Livia", "professionId": 4, "campaignId": 4, "unlock": "Eye of the North — Shining Blade quest" },
  { "id": 22, "name": "Hayda", "professionId": 9, "campaignId": 4, "unlock": "Eye of the North — Ebon Vanguard quest" },
  { "id": 23, "name": "Kahmu", "professionId": 10, "campaignId": 4, "unlock": "Eye of the North — Norn quest" },
  { "id": 24, "name": "Gwen", "professionId": 5, "campaignId": 4, "unlock": "Eye of the North — story" },
  { "id": 25, "name": "Xandra", "professionId": 8, "campaignId": 4, "unlock": "Eye of the North — quest (requires Factions on account for full use)" },
  { "id": 26, "name": "Vekk", "professionId": 6, "campaignId": 4, "unlock": "Eye of the North — story, Asura questline" },
  { "id": 27, "name": "Ogden Stonehealer", "professionId": 3, "campaignId": 4, "unlock": "Eye of the North — story, Deldrimor questline" },
  { "id": 36, "name": "Miku", "professionId": 7, "campaignId": 2, "unlock": "Guild Wars Beyond — Winds of Change (Factions)" },
  { "id": 37, "name": "Zei Ri", "professionId": 8, "campaignId": 2, "unlock": "Guild Wars Beyond — Winds of Change (Factions)" }
]
